pygros.cpython-313-darwin.so
pygros-0.2.0.dist-info/RECORD
pygros-0.2.0.dist-info/WHEEL
pygros-0.2.0.dist-info/top_level.txt
pygros-0.2.0.dist-info/METADATA
pygros-0.2.0.dist-info/licenses/LICENSE
